{"student_id":"3e07c04c-08c5-45b2-895f-bc38d88c0f53","short_code":"TTA5XB","concern_flags":["never_correct_target"],"top_blockers":[],"activities":[{"activity_id":"c7ad86bf-1218-4909-95b9-af0d2e5ea121","unit":"1","lesson":"1","text_title":"Eleven","activity_type":"literal_comp","concern_type":"never_correct_target","summary":{"questions_attempted":4,"reached_target_task":true,"pct_correct_first":0.0,"pct_needed_scaffolding":0.0,"pct_never_correct":100.0,"target_task_correct":0,"target_task_count":2,"blocker_counts":{}},"questions":[{"question_label":"Question 3","question":"Highlight a sentence or phrase from the text that supports your answer to Part A.","section":0,"step":2,"mojo_standard":"MOJO.CITE-EVIDENCE","correct_first":false,"eventually_correct":false,"needed_scaffolding":false,"never_correct":true,"final_bucket":null,"attempt_count":3,"responses":[{"attempt_num":1,"content":"I hate you purple ball","bucket_label":null,"bucket_rationale":null,"point_value":null,"points_possible":3,"canonical_blocker":null},{"attempt_num":2,"content":"shut upppppppppppppppppp","bucket_label":null,"bucket_rationale":null,"point_value":null,"points_possible":3,"canonical_blocker":null},{"attempt_num":3,"content":"she was going to tell Mrs. price that it wasn't hers","bucket_label":null,"bucket_rationale":null,"point_value":2,"points_possible":3,"canonical_blocker":null}]},{"question_label":"Question 5","question":"Part A: Which of the following abilities does the narrator mainly believe older people have that younger people don't?","section":0,"step":4,"mojo_standard":"MOJO.ANALYZE-CRAFT","correct_first":false,"eventually_correct":false,"needed_scaffolding":false,"never_correct":true,"final_bucket":null,"attempt_count":1,"responses":[{"attempt_num":1,"content":"she starts crying","bucket_label":null,"bucket_rationale":null,"point_value":3,"points_possible":3,"canonical_blocker":null}]},{"question_label":"Question 7","question":" Part A: What is the main conflict Rachel faces in the story?","section":1,"step":0,"mojo_standard":"MOJO.SYNTHESIZE","correct_first":false,"eventually_correct":false,"needed_scaffolding":false,"never_correct":true,"final_bucket":null,"attempt_count":1,"responses":[{"attempt_num":1,"content":"","bucket_label":null,"bucket_rationale":null,"point_value":1,"points_possible":1,"canonical_blocker":null}]},{"question_label":"Question 8","question":"Part B: Which evidence from the text BEST shows how Rachel responds to this conflict?","section":1,"step":1,"mojo_standard":"MOJO.SYNTHESIZE","correct_first":false,"eventually_correct":false,"needed_scaffolding":false,"never_correct":true,"final_bucket":null,"attempt_count":1,"responses":[{"attempt_num":1,"content":"","bucket_label":null,"bucket_rationale":null,"point_value":0,"points_possible":1,"canonical_blocker":null}]}]},{"activity_id":"3fdf797c-0cac-451d-ac1c-a2a0b56e4734","unit":"1","lesson":"2","text_title":"Eleven","activity_type":"language","concern_type":"never_correct_target","summary":{"questions_attempted":4,"reached_target_task":true,"pct_correct_first":0.0,"pct_needed_scaffolding":0.0,"pct_never_correct":100.0,"target_task_correct":0,"target_task_count":1,"blocker_counts":{}},"questions":[{"question_label":"Question 3","question":"What claim does Sylvia make about the sweater in paragraph 9?","section":0,"step":2,"mojo_standard":"MOJO.ANALYZE-ARGUMENT","correct_first":false,"eventually_correct":false,"needed_scaffolding":false,"never_correct":true,"final_bucket":null,"attempt_count":1,"responses":[{"attempt_num":1,"content":"she said maybe its a thousand years old even if it was hers she would say no,and its itchy","bucket_label":null,"bucket_rationale":null,"point_value":3,"points_possible":3,"canonical_blocker":null}]},{"question_label":"Question 4","question":"How does Rachel react when Sylvia makes this claim?","section":0,"step":3,"mojo_standard":"MOJO.ANALYZE-ARGUMENT","correct_first":false,"eventually_correct":false,"needed_scaffolding":false,"never_correct":true,"final_bucket":null,"attempt_count":1,"responses":[{"attempt_num":1,"content":"she said it belonged to Rachel a ugly sweater like that all raggedy and old","bucket_label":null,"bucket_rationale":null,"point_value":3,"points_possible":3,"canonical_blocker":null}]},{"question_label":"Question 5","question":"Highlight a sentence from paragraphs 18-19 that describes Rachel's physical reaction to wearing the sweater.","section":0,"step":4,"mojo_standard":"MOJO.ANALYZE-CHARACTER","correct_first":false,"eventually_correct":false,"needed_scaffolding":false,"never_correct":true,"final_bucket":null,"attempt_count":3,"responses":[{"attempt_num":1,"content":"I don't know","bucket_label":null,"bucket_rationale":null,"point_value":null,"points_possible":3,"canonical_blocker":null},{"attempt_num":2,"content":"she thinks she is stupid and a liar","bucket_label":null,"bucket_rationale":null,"point_value":1,"points_possible":3,"canonical_blocker":null},{"attempt_num":3,"content":"Maybe because I'm skinny, maybe because she doesn't like me, that stupid","bucket_label":null,"bucket_rationale":null,"point_value":2,"points_possible":3,"canonical_blocker":null}]},{"question_label":"Question 8","question":"How does Rachel feel when Sylvia says the sweater belongs to her, and why does she feel this way? \n\nRespond to this question in the form of a paragraph that includes a claim, evidence from paragraphs 8-11, and explanation.","section":1,"step":1,"mojo_standard":"MOJO.SYNTHESIZE","correct_first":false,"eventually_correct":false,"needed_scaffolding":false,"never_correct":true,"final_bucket":null,"attempt_count":3,"responses":[{"attempt_num":1,"content":"she wishes to be a runaway balloon","bucket_label":null,"bucket_rationale":null,"point_value":1,"points_possible":3,"canonical_blocker":null},{"attempt_num":2,"content":"She feels like she\u2019s three and she is crying in front of her class for a sweafter that wasn\u2019t her\u2019s","bucket_label":null,"bucket_rationale":null,"point_value":1,"points_possible":3,"canonical_blocker":null},{"attempt_num":3,"content":"She wishes she wasn\u2019t eleven","bucket_label":null,"bucket_rationale":null,"point_value":1,"points_possible":3,"canonical_blocker":null}]}]},{"activity_id":"7a452026-5ea7-46ff-9469-b24b077ba157","unit":"1","lesson":"3","text_title":"Eleven","activity_type":"language","concern_type":"never_correct_target","summary":{"questions_attempted":4,"reached_target_task":true,"pct_correct_first":0.0,"pct_needed_scaffolding":0.0,"pct_never_correct":100.0,"target_task_correct":0,"target_task_count":2,"blocker_counts":{}},"questions":[{"question_label":"Question 2","question":"Re-read the following line from paragraph 14:\n\n\u201cExcept when math period ends Mrs. Price says loud and in front of everybody, \u2018Now, Rachel, that's enough,\u2019 because she sees I've shoved the red sweater to the tippy-tip corner of my desk and it's hanging over the edge like a waterfall, but I don't care.\u201d\n\nWhat specific characteristic do waterfalls and the hanging sweater share that makes this comparison effective?","section":0,"step":1,"mojo_standard":"MOJO.ANALYZE-CHARACTER","correct_first":false,"eventually_correct":false,"needed_scaffolding":false,"never_correct":true,"final_bucket":null,"attempt_count":2,"responses":[{"attempt_num":1,"content":"It\u2019s like a jump rope","bucket_label":null,"bucket_rationale":null,"point_value":1,"points_possible":3,"canonical_blocker":null},{"attempt_num":2,"content":"She is hanging on the edge Like a waterfall","bucket_label":null,"bucket_rationale":null,"point_value":3,"points_possible":3,"canonical_blocker":null}]},{"question_label":"Question 3","question":"In paragraph 19, Rachel says she's \u201ccrying like I'm three in front of everybody.\u201d This comparison is an example of:","section":0,"step":2,"mojo_standard":"MOJO.ANALYZE-CHARACTER","correct_first":false,"eventually_correct":false,"needed_scaffolding":false,"never_correct":true,"final_bucket":null,"attempt_count":3,"responses":[{"attempt_num":1,"content":"She hates the sweater and it\u2019s not her\u2019s","bucket_label":null,"bucket_rationale":null,"point_value":1,"points_possible":3,"canonical_blocker":null},{"attempt_num":2,"content":"The sweater was hanging in the tippy tip of the desk and it was hanging like a waterfall.","bucket_label":null,"bucket_rationale":null,"point_value":2,"points_possible":3,"canonical_blocker":null},{"attempt_num":3,"content":"Both waterfall and the sweater flow were hanging downward from a higher place.","bucket_label":null,"bucket_rationale":null,"point_value":3,"points_possible":3,"canonical_blocker":null}]},{"question_label":"Question 5","question":"How does the figurative language in paragraph 14 help readers understand Rachel's reaction to the sweater?","section":1,"step":0,"mojo_standard":"MOJO.SYNTHESIZE","correct_first":false,"eventually_correct":false,"needed_scaffolding":false,"never_correct":true,"final_bucket":null,"attempt_count":1,"responses":[{"attempt_num":1,"content":"A. The simile in the paragraph helps readers understand how Rachel feels about the sweater.\n","bucket_label":null,"bucket_rationale":null,"point_value":1,"points_possible":1,"canonical_blocker":null}]},{"question_label":"Question 6","question":"How does the figurative language in paragraph 19 help readers visualize Rachel's behavior?","section":1,"step":1,"mojo_standard":"MOJO.SYNTHESIZE","correct_first":false,"eventually_correct":false,"needed_scaffolding":false,"never_correct":true,"final_bucket":null,"attempt_count":1,"responses":[{"attempt_num":1,"content":"C. The similes about her body shaking \u201clike when you have the hiccups\u201d and her head hurting \u201clike when you drink milk too fast\u201d connect to unpleasant experiences most readers have had.\n","bucket_label":null,"bucket_rationale":null,"point_value":1,"points_possible":1,"canonical_blocker":null}]}]},{"activity_id":"d63ef4a1-a52c-40b7-8dd6-a358bb6d8064","unit":"1","lesson":"4","text_title":"Eleven","activity_type":"closeread","concern_type":"never_correct_target","summary":{"questions_attempted":1,"reached_target_task":true,"pct_correct_first":0.0,"pct_needed_scaffolding":0.0,"pct_never_correct":100.0,"target_task_correct":0,"target_task_count":1,"blocker_counts":{}},"questions":[{"question_label":"Question 8","question":"How does the author's use of figurative language help readers understand the explicit and implicit feelings that the narrator is expressing? \n\nRespond to this question in the form of a paragraph that includes a claim, evidence, and explanation.","section":1,"step":0,"mojo_standard":"MOJO.SYNTHESIZE","correct_first":false,"eventually_correct":false,"needed_scaffolding":false,"never_correct":true,"final_bucket":null,"attempt_count":3,"responses":[{"attempt_num":1,"content":"the author use of figurative language helps the reader understand what rachle is feeling","bucket_label":null,"bucket_rationale":null,"point_value":1,"points_possible":3,"canonical_blocker":null},{"attempt_num":2,"content":"the figurative language describes rachles strong feelings about the teacher and sweater","bucket_label":null,"bucket_rationale":null,"point_value":1,"points_possible":3,"canonical_blocker":null},{"attempt_num":3,"content":"the figurative language describes Rachel strong feelings about the teacher and sweater:it has to be long to somebody,\" Mrs.price keeps saying,but nobody can remember.it's a ugly  sweater with red plastic buttons and a collar and sleeves all stretched out like you could use it for a jump rope.it's maybe a thousand years old even if it belonged to me I wouldn't say so. Rachel used a smile to a jump rope she makes this comparison to show her dislike of thee sweater. \"I'm eleven and it's my birthday today and i'm crying like i'm three in front of everybody.''","bucket_label":null,"bucket_rationale":null,"point_value":2,"points_possible":3,"canonical_blocker":null}]}]},{"activity_id":"b5059156-428b-4eb6-9b75-61ddf4ba951b","unit":"1","lesson":"8","text_title":"The Mighty Miss Malone","activity_type":"language","concern_type":"never_correct_target","summary":{"questions_attempted":4,"reached_target_task":true,"pct_correct_first":0.0,"pct_needed_scaffolding":0.0,"pct_never_correct":100.0,"target_task_correct":0,"target_task_count":2,"blocker_counts":{}},"questions":[{"question_label":"Question 2","question":"Based on Mrs. Scott's actions in paragraphs 12 and 13, the reader can conclude that________","section":0,"step":1,"mojo_standard":"MOJO.ANALYZE-CHARACTER","correct_first":false,"eventually_correct":false,"needed_scaffolding":false,"never_correct":true,"final_bucket":null,"attempt_count":1,"responses":[{"attempt_num":1,"content":"She thinks that Mrs.scott want her to help her classmates","bucket_label":null,"bucket_rationale":null,"point_value":3,"points_possible":3,"canonical_blocker":null}]},{"question_label":"Question 5","question":"How does Deza's lack of awareness about Mrs. Scott's suspicions affect the tension in this scene?","section":0,"step":4,"mojo_standard":"MOJO.ANALYZE-CHARACTER","correct_first":false,"eventually_correct":false,"needed_scaffolding":false,"never_correct":true,"final_bucket":null,"attempt_count":1,"responses":[{"attempt_num":1,"content":"She though she cheated on the test and wanted her to show more proof that she did the test herself","bucket_label":null,"bucket_rationale":null,"point_value":3,"points_possible":3,"canonical_blocker":null}]},{"question_label":"Question 6","question":"Deza's reaction to Mrs. Scott's request reveals that Deza \u2014","section":1,"step":0,"mojo_standard":"MOJO.SYNTHESIZE","correct_first":false,"eventually_correct":false,"needed_scaffolding":false,"never_correct":true,"final_bucket":null,"attempt_count":1,"responses":[{"attempt_num":1,"content":"C. is not aware that Mrs. Scott thinks she might have cheated on her test.\n","bucket_label":null,"bucket_rationale":null,"point_value":1,"points_possible":1,"canonical_blocker":null}]},{"question_label":"Question 7","question":"Which paragraph best shows evidence for the answer to to the previous question?","section":1,"step":1,"mojo_standard":"MOJO.SYNTHESIZE","correct_first":false,"eventually_correct":false,"needed_scaffolding":false,"never_correct":true,"final_bucket":null,"attempt_count":1,"responses":[{"attempt_num":1,"content":"C. 15\n","bucket_label":null,"bucket_rationale":null,"point_value":0,"points_possible":1,"canonical_blocker":null}]}]},{"activity_id":"ee4031e0-909f-40f7-bb1b-5d27eb0fd39b","unit":"1","lesson":"10","text_title":"Red Scarf Girl","activity_type":"literal_comp","concern_type":"never_correct_target","summary":{"questions_attempted":5,"reached_target_task":true,"pct_correct_first":0.0,"pct_needed_scaffolding":0.0,"pct_never_correct":100.0,"target_task_correct":0,"target_task_count":2,"blocker_counts":{}},"questions":[{"question_label":"Question 2","question":"In paragraph 8, Teacher Zhang mentions that Ji-li \u201cparticipates in educational reform\u201d. What inference can be made about his motivation for bringing this up?","section":0,"step":1,"mojo_standard":"MOJO.ANALYZE-CHARACTER","correct_first":false,"eventually_correct":false,"needed_scaffolding":false,"never_correct":true,"final_bucket":null,"attempt_count":1,"responses":[{"attempt_num":1,"content":"Because they are exposing her dad in front of her teachers and the school","bucket_label":null,"bucket_rationale":null,"point_value":3,"points_possible":3,"canonical_blocker":null}]},{"question_label":"Question 3","question":"Read the following passage from paragraph 10:\n\n\u201cI closed my eyes. I saw Dad standing on a stage, his head bowed, his name written in large black letters, and then crossed out in red ink, on a sign hanging from his neck. I saw myself standing in the middle of the stage, facing thousands of people, condemning Dad for his crimes, raising my fist to lead the chant, \u2018Down with Jiang Xi-reng.\u2019 I saw Dad looking at me hopelessly, tears on his face.\u201d\n\nWhat does this suggest about Ji-li's relationship with her father?","section":0,"step":2,"mojo_standard":"MOJO.ANALYZE-CHARACTER","correct_first":false,"eventually_correct":false,"needed_scaffolding":false,"never_correct":true,"final_bucket":null,"attempt_count":3,"responses":[{"attempt_num":1,"content":"He is saying that she isn\u2019t like her father,i think","bucket_label":null,"bucket_rationale":null,"point_value":2,"points_possible":3,"canonical_blocker":null},{"attempt_num":2,"content":"He saying that she is smart and has done so well in school.in a addition of her studies.she participated in education.","bucket_label":null,"bucket_rationale":null,"point_value":2,"points_possible":3,"canonical_blocker":null},{"attempt_num":3,"content":"He thinks she could be beneficial to the goals of the party.","bucket_label":null,"bucket_rationale":null,"point_value":3,"points_possible":3,"canonical_blocker":null}]},{"question_label":"Question 5","question":"Which of the following inferences about the interrogation is best supported by the text?","section":0,"step":4,"mojo_standard":"MOJO.ANALYZE-CHARACTER","correct_first":false,"eventually_correct":false,"needed_scaffolding":false,"never_correct":true,"final_bucket":null,"attempt_count":2,"responses":[{"attempt_num":1,"content":"She felt like everything was closing in around her and rain shows her sadness","bucket_label":null,"bucket_rationale":null,"point_value":2,"points_possible":3,"canonical_blocker":null},{"attempt_num":2,"content":"She feels trappped and hopeless and like a small animal","bucket_label":null,"bucket_rationale":null,"point_value":3,"points_possible":3,"canonical_blocker":null}]},{"question_label":"Question 7","question":"Which of the following best expresses a central idea of the excerpt?","section":1,"step":0,"mojo_standard":"MOJO.SYNTHESIZE","correct_first":false,"eventually_correct":false,"needed_scaffolding":false,"never_correct":true,"final_bucket":null,"attempt_count":1,"responses":[{"attempt_num":1,"content":"C. If someone does not do what the Communists tell them, they are likely to face a harsh punishment.\n","bucket_label":null,"bucket_rationale":null,"point_value":1,"points_possible":1,"canonical_blocker":null}]},{"question_label":"Question 8","question":"Which sentence from the text most strongly supports the answer to the previous question?","section":1,"step":1,"mojo_standard":"MOJO.SYNTHESIZE","correct_first":false,"eventually_correct":false,"needed_scaffolding":false,"never_correct":true,"final_bucket":null,"attempt_count":1,"responses":[{"attempt_num":1,"content":"D. \u201cIf you want to make a clean break with your black family, then you can be an educable child and we will welcome you to our revolutionary ranks.\u201d\n","bucket_label":null,"bucket_rationale":null,"point_value":0,"points_possible":1,"canonical_blocker":null}]}]},{"activity_id":"4d4a718f-c829-475c-89df-a60b62774f1f","unit":"1","lesson":"11","text_title":"Hatchet","activity_type":"literal_comp","concern_type":"never_correct_target","summary":{"questions_attempted":4,"reached_target_task":true,"pct_correct_first":0.0,"pct_needed_scaffolding":0.0,"pct_never_correct":100.0,"target_task_correct":0,"target_task_count":2,"blocker_counts":{}},"questions":[{"question_label":"Question 2","question":"The repetition of the phrase \u201cthey would\u201d in paragraphs 1-3 mainly suggests that Brian____","section":0,"step":1,"mojo_standard":"MOJO.ANALYZE-CHARACTER","correct_first":false,"eventually_correct":false,"needed_scaffolding":false,"never_correct":true,"final_bucket":null,"attempt_count":3,"responses":[{"attempt_num":1,"content":"They would look for him, look for the plane. His father and mother would be frantic. They would tear the world apart to find him. Brian had seen searches on the news, seen movies about lost planes. When a plane went down they mounted extensive searches and almost always they found the plane within a day or two. Pilots all filed flight plans\u2014a detailed plan for where and when they were going to fly, with all the courses explained. They would come, they would look for him. The searchers would get government planes and cover both sides of the flight plan filed by the pilot and search until they found him.\nMaybe even today. They might come today. This was the second day after the crash. No. Brian frowned. Was it the first day or the second day? They had gone down in the afternoon and he had spent the whole night out cold. So this was the first real day. But they could still come today. They would have started the search immediately when Brian's plane did not arrive.","bucket_label":null,"bucket_rationale":null,"point_value":1,"points_possible":3,"canonical_blocker":null},{"attempt_num":2,"content":"He was on a island with nothing to eat and alone.","bucket_label":null,"bucket_rationale":null,"point_value":2,"points_possible":3,"canonical_blocker":null},{"attempt_num":3,"content":"The rescuers would look for him and the plane.his parents would even tear the world to apart to find him.","bucket_label":null,"bucket_rationale":null,"point_value":2,"points_possible":3,"canonical_blocker":null}]},{"question_label":"Question 5","question":"Highlight a detail that shows Mr. Perpich was an optimistic man who believed in his students.","section":0,"step":4,"mojo_standard":"MOJO.ANALYZE-CHARACTER","correct_first":false,"eventually_correct":false,"needed_scaffolding":false,"never_correct":true,"final_bucket":null,"attempt_count":3,"responses":[{"attempt_num":1,"content":"A person who is always talking positively,thinking positive,staying on top of things.","bucket_label":null,"bucket_rationale":null,"point_value":2,"points_possible":3,"canonical_blocker":null},{"attempt_num":2,"content":"To never give up ,and think positively","bucket_label":null,"bucket_rationale":null,"point_value":2,"points_possible":3,"canonical_blocker":null},{"attempt_num":3,"content":"Stay on top of things.stay positive","bucket_label":null,"bucket_rationale":null,"point_value":2,"points_possible":3,"canonical_blocker":null}]},{"question_label":"Question 7","question":"What is the main conflict Brian faces in this excerpt from Hatchet?","section":1,"step":0,"mojo_standard":"MOJO.SYNTHESIZE","correct_first":false,"eventually_correct":false,"needed_scaffolding":false,"never_correct":true,"final_bucket":null,"attempt_count":3,"responses":[{"attempt_num":1,"content":"He stills thinks that he will get rescued at late night or early morning","bucket_label":null,"bucket_rationale":null,"point_value":2,"points_possible":3,"canonical_blocker":null},{"attempt_num":2,"content":"He doesn\u2019t have anything to eat","bucket_label":null,"bucket_rationale":null,"point_value":2,"points_possible":3,"canonical_blocker":null},{"attempt_num":3,"content":"He\u2019s looking in his pockets to find something useful like a source of food, and the only thing he finds is a slight bit of currency such as dimes coins and a quarter and something that could be extremely helpful such as his hatchet, and what he could do with that hatchet he could get longs and rub sticks atop of the logs and make a fire to comfort comfort him once it becomes midnight","bucket_label":null,"bucket_rationale":null,"point_value":3,"points_possible":3,"canonical_blocker":null}]},{"question_label":"Question 8","question":"Which detail from the text best supports your answer to the previous question?","section":1,"step":1,"mojo_standard":"MOJO.SYNTHESIZE","correct_first":false,"eventually_correct":false,"needed_scaffolding":false,"never_correct":true,"final_bucket":null,"attempt_count":1,"responses":[{"attempt_num":1,"content":"C. \u201cThe trouble, Brian thought, looking around, was that all he could see was grass and brush. There was nothing obvious to eat.\u201d\n","bucket_label":null,"bucket_rationale":null,"point_value":1,"points_possible":1,"canonical_blocker":null}]}]},{"activity_id":"37857abf-9105-45f5-ba81-9bd441e01188","unit":"1","lesson":"12","text_title":"Hatchet","activity_type":"closeread","concern_type":"never_correct_target","summary":{"questions_attempted":5,"reached_target_task":true,"pct_correct_first":0.0,"pct_needed_scaffolding":0.0,"pct_never_correct":100.0,"target_task_correct":0,"target_task_count":2,"blocker_counts":{}},"questions":[{"question_label":"Question 2","question":"What do Brian's expectations of rescue reveal about how he views his current setting?","section":0,"step":1,"mojo_standard":"MOJO.ANALYZE-CHARACTER","correct_first":false,"eventually_correct":false,"needed_scaffolding":false,"never_correct":true,"final_bucket":null,"attempt_count":2,"responses":[{"attempt_num":1,"content":"Brain thinks the plane will come today or tommarow","bucket_label":null,"bucket_rationale":null,"point_value":2,"points_possible":3,"canonical_blocker":null},{"attempt_num":2,"content":"The amphibious planes,bush planes with floats that could land right here.on the lake and pick him up and take brain home.","bucket_label":null,"bucket_rationale":null,"point_value":3,"points_possible":3,"canonical_blocker":null}]},{"question_label":"Question 3","question":"Reread paragraphs 7-9. Why does Brian evaluate his surroundings so carefully?","section":0,"step":2,"mojo_standard":"MOJO.ANALYZE-CHARACTER","correct_first":false,"eventually_correct":false,"needed_scaffolding":false,"never_correct":true,"final_bucket":null,"attempt_count":3,"responses":[{"attempt_num":1,"content":"They will be bush planes with floats","bucket_label":null,"bucket_rationale":null,"point_value":2,"points_possible":3,"canonical_blocker":null},{"attempt_num":2,"content":"They will land at the lake with floats and pick him up and take him home.","bucket_label":null,"bucket_rationale":null,"point_value":2,"points_possible":3,"canonical_blocker":null},{"attempt_num":3,"content":"He thinks Either way he would probably be home by late night or early morning","bucket_label":null,"bucket_rationale":null,"point_value":2,"points_possible":3,"canonical_blocker":null}]},{"question_label":"Question 4","question":"How does the setting in paragraphs 12-14 cause Brian to change from feeling hopeless to taking action?","section":0,"step":3,"mojo_standard":"MOJO.ANALYZE-CHARACTER","correct_first":false,"eventually_correct":false,"needed_scaffolding":false,"never_correct":true,"final_bucket":null,"attempt_count":3,"responses":[{"attempt_num":1,"content":"He rubbed his stomach.the hunger had been there but something else fear,pain had held it down.Now,with the thought of the Buger,the emptiness roared at him.he could not believe the hunger,had never felt it this way.","bucket_label":null,"bucket_rationale":null,"point_value":2,"points_possible":3,"canonical_blocker":null},{"attempt_num":2,"content":"He was starving wishing to eat a burger while he was with fear and pain wanting to go home","bucket_label":null,"bucket_rationale":null,"point_value":2,"points_possible":3,"canonical_blocker":null},{"attempt_num":3,"content":"There he was,he thought.absolutely nothing to eat.nothing","bucket_label":null,"bucket_rationale":null,"point_value":2,"points_possible":3,"canonical_blocker":null}]},{"question_label":"Question 7","question":"This part of the story takes place in the wilderness. What challenge does this setting create for Brian?","section":1,"step":0,"mojo_standard":"MOJO.SYNTHESIZE","correct_first":false,"eventually_correct":false,"needed_scaffolding":false,"never_correct":true,"final_bucket":null,"attempt_count":1,"responses":[{"attempt_num":1,"content":"B. The setting's dangerous wildlife threatens Brian's physical safety throughout the excerpt\n","bucket_label":null,"bucket_rationale":null,"point_value":0,"points_possible":1,"canonical_blocker":null}]},{"question_label":"Question 8","question":"Which detail from the text best supports the answer to the previous question?","section":1,"step":1,"mojo_standard":"MOJO.SYNTHESIZE","correct_first":false,"eventually_correct":false,"needed_scaffolding":false,"never_correct":true,"final_bucket":null,"attempt_count":1,"responses":[{"attempt_num":1,"content":"A. \u201cAnd there was, he thought, absolutely nothing to eat. Nothing.\u201d \n","bucket_label":null,"bucket_rationale":null,"point_value":1,"points_possible":1,"canonical_blocker":null}]}]},{"activity_id":"419dc67a-275e-4150-94a1-7cddc44ec0ad","unit":"1","lesson":"13","text_title":"Red Scarf Girl\nHatchet","activity_type":"writing","concern_type":"never_correct_target","summary":{"questions_attempted":2,"reached_target_task":true,"pct_correct_first":0.0,"pct_needed_scaffolding":0.0,"pct_never_correct":100.0,"target_task_correct":0,"target_task_count":1,"blocker_counts":{}},"questions":[{"question_label":"Question 6","question":"Based on the evidence you've gathered, what is the biggest difference between how the wilderness setting affects Brian and how the school setting affects Jiang?","section":0,"step":5,"mojo_standard":"MOJO.ANALYZE-CHARACTER","correct_first":false,"eventually_correct":false,"needed_scaffolding":false,"never_correct":true,"final_bucket":null,"attempt_count":3,"responses":[{"attempt_num":1,"content":"THEY BOTH FEEL. FEAR AND WANT TO GO HOME","bucket_label":null,"bucket_rationale":null,"point_value":2,"points_possible":3,"canonical_blocker":null},{"attempt_num":2,"content":"BOTH OF THEM ARE IN TOUGH  SITUATIONS","bucket_label":null,"bucket_rationale":null,"point_value":2,"points_possible":3,"canonical_blocker":null},{"attempt_num":3,"content":"found myself in a narrow passageway between the school building and the school-yard wall. The gray concrete walls closed around me and a slow drizzle dampened my cheeks. I could not go back to the classroom, and I could not go home. I felt like a small animal that had fallen into a trap, alone and helpless, and sure that the hunter was coming.","bucket_label":null,"bucket_rationale":null,"point_value":2,"points_possible":3,"canonical_blocker":null}]},{"question_label":"Question 7","question":"Consider all the evidence you gathered about how setting influences Brian and Jiang. In one sentence, write a claim that compares and contrasts the role that setting plays in influencing the characters and events in both texts. \n\nYour claim should address both similarities and differences in how the wilderness setting in \u201cHatchet\u201d and the school setting in \u201cRed Scarf Girl\u201d affect the characters.","section":1,"step":0,"mojo_standard":"MOJO.SYNTHESIZE","correct_first":false,"eventually_correct":false,"needed_scaffolding":false,"never_correct":true,"final_bucket":null,"attempt_count":3,"responses":[{"attempt_num":1,"content":"This is what I think:they are alone so   they\u2019re low-key the same cause they both are alone and they don\u2019t have no one with them cause they don\u2019t know the situation so they feel scared cause you\u2019re so quiet and they just wanna go home but they can\u2019t go cause they\u2019re in a big situation that they can himself and feel kind of small and wish they could just be home with the situation they\u2019re in.so both of them are in a tough situation. They can\u2019t do anything so they feel like they don\u2019t really have hope","bucket_label":null,"bucket_rationale":null,"point_value":2,"points_possible":3,"canonical_blocker":null},{"attempt_num":2,"content":"Brian feels hungry and he felt scared cause he\u2019s unloaded and he tries to take positive Because Mr. purpich  he has heard Mr. purpich say that that to stay on top of things,to think positive if you\u2019re in a tough situation to think positive.the girl doesn\u2019t know what to do","bucket_label":null,"bucket_rationale":null,"point_value":2,"points_possible":3,"canonical_blocker":null},{"attempt_num":3,"content":"They both are alone and feel different ways and scared","bucket_label":null,"bucket_rationale":null,"point_value":2,"points_possible":3,"canonical_blocker":null}]}]},{"activity_id":"bca7d714-2cda-4369-9533-4c531ad4e3c0","unit":"1","lesson":"17","text_title":"Scout's Honor","activity_type":"literal_comp","concern_type":null,"summary":{"questions_attempted":2,"reached_target_task":false,"pct_correct_first":0.0,"pct_needed_scaffolding":0.0,"pct_never_correct":100.0,"target_task_correct":null,"target_task_count":null,"blocker_counts":{}},"questions":[{"question_label":"Question 4","question":"Based on paragraphs 30-32, which boy is the **least** prepared for the camping trip?","section":0,"step":3,"mojo_standard":"MOJO.ANALYZE-CHARACTER","correct_first":false,"eventually_correct":false,"needed_scaffolding":false,"never_correct":true,"final_bucket":null,"attempt_count":3,"responses":[{"attempt_num":1,"content":"Max doesnt want his friends because he thinks he is not strong enough","bucket_label":null,"bucket_rationale":null,"point_value":1,"points_possible":3,"canonical_blocker":null},{"attempt_num":2,"content":"Max doesnt want his friends to think he is not strong enough","bucket_label":null,"bucket_rationale":null,"point_value":2,"points_possible":3,"canonical_blocker":null},{"attempt_num":3,"content":"Sesint","bucket_label":null,"bucket_rationale":null,"point_value":2,"points_possible":3,"canonical_blocker":null}]},{"question_label":"Question 5","question":"Which inference about the narrator and his friends is most strongly supported by the story?","section":0,"step":4,"mojo_standard":"MOJO.ANALYZE-CRAFT","correct_first":false,"eventually_correct":false,"needed_scaffolding":false,"never_correct":true,"final_bucket":null,"attempt_count":3,"responses":[{"attempt_num":1,"content":"Scared ov reds","bucket_label":null,"bucket_rationale":null,"point_value":1,"points_possible":3,"canonical_blocker":null},{"attempt_num":2,"content":"They have canned food and a blanket","bucket_label":null,"bucket_rationale":null,"point_value":2,"points_possible":3,"canonical_blocker":null},{"attempt_num":3,"content":"Idk","bucket_label":null,"bucket_rationale":null,"point_value":2,"points_possible":3,"canonical_blocker":null}]}]},{"activity_id":"43d497fd-04e9-4868-952d-8c1a48578d41","unit":"1","lesson":"18","text_title":"Scout's Honor","activity_type":"language","concern_type":"never_correct_target","summary":{"questions_attempted":4,"reached_target_task":true,"pct_correct_first":0.0,"pct_needed_scaffolding":0.0,"pct_never_correct":100.0,"target_task_correct":0,"target_task_count":2,"blocker_counts":{}},"questions":[{"question_label":"Question 2","question":"Reread paragraph 81. Based on this paragraph, what can the reader conclude about the narrator?","section":0,"step":1,"mojo_standard":"MOJO.ANALYZE-CRAFT","correct_first":false,"eventually_correct":false,"needed_scaffolding":false,"never_correct":true,"final_bucket":null,"attempt_count":2,"responses":[{"attempt_num":1,"content":"That they are going to New York or new jersey","bucket_label":null,"bucket_rationale":null,"point_value":2,"points_possible":3,"canonical_blocker":null},{"attempt_num":2,"content":"He said that he thinks,that him and his friends are lost","bucket_label":null,"bucket_rationale":null,"point_value":3,"points_possible":3,"canonical_blocker":null}]},{"question_label":"Question 4","question":"Look closely at paragraphs 89-95. Highlight a detail that supports your answer to the previous question.","section":0,"step":3,"mojo_standard":"MOJO.ANALYZE-CHARACTER","correct_first":false,"eventually_correct":false,"needed_scaffolding":false,"never_correct":true,"final_bucket":null,"attempt_count":3,"responses":[{"attempt_num":1,"content":"It started raining and his blanket got soaked and it was very dark","bucket_label":null,"bucket_rationale":null,"point_value":2,"points_possible":3,"canonical_blocker":null},{"attempt_num":2,"content":"He folded the umbrella so he and his friends would get soak equally","bucket_label":null,"bucket_rationale":null,"point_value":2,"points_possible":3,"canonical_blocker":null},{"attempt_num":3,"content":"I think the narrator was trying to make it funny that they all soaked eachother","bucket_label":null,"bucket_rationale":null,"point_value":2,"points_possible":3,"canonical_blocker":null}]},{"question_label":"Question 6","question":"Which of the following best describes the theme of \u201cScout's Honor\u201d?","section":1,"step":0,"mojo_standard":"MOJO.SYNTHESIZE","correct_first":false,"eventually_correct":false,"needed_scaffolding":false,"never_correct":true,"final_bucket":null,"attempt_count":1,"responses":[{"attempt_num":1,"content":"D.  In life, we sometimes take on more than we can handle.\n","bucket_label":null,"bucket_rationale":null,"point_value":1,"points_possible":1,"canonical_blocker":null}]},{"question_label":"Question 7","question":"What role does this passage play in the overall story structure?","section":1,"step":1,"mojo_standard":"MOJO.SYNTHESIZE","correct_first":false,"eventually_correct":false,"needed_scaffolding":false,"never_correct":true,"final_bucket":null,"attempt_count":1,"responses":[{"attempt_num":1,"content":"A. The events in the passage highlight the turning point of the plot because the boys are afraid.\n","bucket_label":null,"bucket_rationale":null,"point_value":0,"points_possible":1,"canonical_blocker":null}]}]},{"activity_id":"7ab843dc-714b-4134-ae00-c8e7cd85b561","unit":"2","lesson":"4","text_title":"Walk Two Moons","activity_type":"closeread","concern_type":null,"summary":{"questions_attempted":1,"reached_target_task":false,"pct_correct_first":0.0,"pct_needed_scaffolding":0.0,"pct_never_correct":100.0,"target_task_correct":null,"target_task_count":null,"blocker_counts":{}},"questions":[{"question_label":"Question 3","question":"What does Sal learn about herself while watching this family interaction?","section":0,"step":2,"mojo_standard":"MOJO.ANALYZE-CHARACTER","correct_first":false,"eventually_correct":false,"needed_scaffolding":false,"never_correct":true,"final_bucket":null,"attempt_count":2,"responses":[{"attempt_num":1,"content":"MISS I MISS U","bucket_label":null,"bucket_rationale":null,"point_value":null,"points_possible":3,"canonical_blocker":null},{"attempt_num":2,"content":":[","bucket_label":null,"bucket_rationale":null,"point_value":null,"points_possible":3,"canonical_blocker":null}]}]}]}